MANIFEST.in
README.txt
setup.py
DAQC2apps.egg-info/PKG-INFO
DAQC2apps.egg-info/SOURCES.txt
DAQC2apps.egg-info/dependency_links.txt
DAQC2apps.egg-info/top_level.txt
piplates/__init__.py
piplates/Applications/DAQC2Motor.ui
piplates/Applications/DAQC2dashboard.py
piplates/Applications/DAQC2plateFunctionGeneratorManual.pdf
piplates/Applications/DAQC2plateMotorControllerManual.pdf
piplates/Applications/DAQC2plateOscilloscopeManual.pdf
piplates/Applications/FunctionGenerator.py
piplates/Applications/FunctionGenerator.ui
piplates/Applications/Oscilloscope.ui
piplates/Applications/QTinstall.py
piplates/Applications/QTmotor.py
piplates/Applications/QTscope.py
piplates/Applications/__init__.py
piplates/Applications/loggerPLOT.py
piplates/Applications/ppLOGGER-Documentation.pdf
piplates/Applications/ppLOGGER2.py
piplates/Applications/py23install.py
piplates/Applications/Assets/DB button.png
piplates/Applications/Assets/FGbutton.png
piplates/Applications/Assets/Icon32X32.png
piplates/Applications/Assets/LoggerButton.png
piplates/Applications/Assets/ScopeButton.png
piplates/Applications/Assets/StepperButton.png
piplates/Applications/Assets/__init__.py
piplates/Applications/Shortcuts/Dashboard.desktop
piplates/Applications/Shortcuts/FG.desktop
piplates/Applications/Shortcuts/Logger.desktop
piplates/Applications/Shortcuts/MOTOR.desktop
piplates/Applications/Shortcuts/Oscope.desktop
piplates/Applications/Shortcuts/__init__.py