Metadata-Version: 1.0
Name: DAQC2apps
Version: 1.000
Summary: Pi-Plates Application Setup
Home-page: https://www.pi-plates.com
Author: Jerry Wasinger, WallyWare, inc.
Author-email: support@pi-plates.com
License: BSD
Keywords: pi-plates,data acquisition,raspberry pi,relays,motors
Platform: UNKNOWN
